README.rst
setup.py
saltobserver/__init__.py
saltobserver/config.py
saltobserver/filters.py
saltobserver/redis_stream.py
saltobserver/views.py
saltobserver/websockets.py
saltobserver.egg-info/PKG-INFO
saltobserver.egg-info/SOURCES.txt
saltobserver.egg-info/dependency_links.txt
saltobserver.egg-info/not-zip-safe
saltobserver.egg-info/requires.txt
saltobserver.egg-info/top_level.txt
saltobserver/static/style.css
saltobserver/templates/base.html
saltobserver/templates/contentpage.html
saltobserver/templates/functionform.html
saltobserver/templates/functions.html
saltobserver/templates/history.html
saltobserver/templates/historyform.html
saltobserver/templates/jobform.html
saltobserver/templates/jobs.html
scripts/run_saltobserver