Metadata-Version: 1.1
Name: saltobserver
Version: 0.9.4
Summary: A simple webapp for presenting data as offered by SaltStack's Redis Returner
Home-page: https://github.com/analogbyte/saltobserver
Author: Daniel Nägele
Author-email: saltobserver@danieln.de
License: MIT
Keywords: saltstack redis returner salt states
Platform: UNKNOWN
Classifier: Development Status :: 4 - Beta
Classifier: Intended Audience :: Developers
Classifier: Intended Audience :: System Administrators
Classifier: Framework :: Flask
Classifier: License :: OSI Approved :: MIT License
Classifier: Programming Language :: Python :: 2
Classifier: Programming Language :: Python :: 2.6
Classifier: Programming Language :: Python :: 2.7
